COVERnant-0.1.data/scripts/covernant
COVERnant-0.1.dist-info/DESCRIPTION.rst
COVERnant-0.1.dist-info/METADATA
COVERnant-0.1.dist-info/RECORD
COVERnant-0.1.dist-info/WHEEL
COVERnant-0.1.dist-info/metadata.json
COVERnant-0.1.dist-info/top_level.txt
covernantlib/__init__.py
covernantlib/bedtowiggle.py
covernantlib/coveragecalculator.py
covernantlib/extract.py
covernantlib/plotmatrix.py
covernantlib/ratio.py
covernantlib/wiggle.py
